LICENSE
README.md
setup.py
database_common_tools.egg-info/PKG-INFO
database_common_tools.egg-info/SOURCES.txt
database_common_tools.egg-info/dependency_links.txt
database_common_tools.egg-info/requires.txt
database_common_tools.egg-info/top_level.txt
databasetools/__init__.py
databasetools/analysis_json.py
databasetools/analysis_json_v2.py
databasetools/analysis_json_v3.py
databasetools/common_utils.py
databasetools/common_utils_v2.py
databasetools/data_analysis.py
databasetools/data_analysis_v2.py
databasetools/data_analysis_v3.py
databasetools/kafka_connect.py
databasetools/log_utils.py
databasetools/mongo_connect.py
databasetools/monitor_process.py
databasetools/mt_wx_message.py
databasetools/mysql_connect.py
databasetools/mysql_connect_v2.py
databasetools/opensearch_connect.py
databasetools/redis_connect.py
databasetools/redis_connect_v2.py
test/__init__.py