Metadata-Version: 2.1
Name: database-common-tools
Version: 1.6.7
Summary: let message middleware and use database more easy
Home-page: https://github.com/yangming9/database-common-tools.git
Author: Coder Yang
Author-email: yma91412@gmail.com
License: MIT
Classifier: License :: OSI Approved :: MIT License
Classifier: Programming Language :: Python
Classifier: Programming Language :: Python :: 3
Classifier: Programming Language :: Python :: 3.6
Classifier: Programming Language :: Python :: Implementation :: CPython
Classifier: Programming Language :: Python :: Implementation :: PyPy
Requires-Python: >=3.6.0
License-File: LICENSE
